<?xml version="1.0" encoding="utf-8"?>
<page id="404">
    <siteName>BoutiqueSenegal</siteName>
    <logo>/e-commerce-front/assets/images/logo.png</logo>
    <title>Page non trouvée</title>
    <css>/e-commerce-front/assets/css/accueil.css</css>
    
    <content>
        <heading>Page introuvable</heading>
        <message>La page demandée n'existe pas ou a été déplacée. Retournez à l'accueil.</message>
        <home href="index.php?page=accueil">Retour à l'accueil</home>
    </content>
</page>
